{
  "info": {
    "description": "data",
    "version": "1.0",
    "year": 2025,
    "contributor": "search engine",
    "source": "no_augmentation",
    "license": {
      "name": "Creative Commons Attribution 4.0 International",
      "url": "https://creativecommons.org/licenses/by/4.0/"
    },
    "leaf_info": {
      "leaf_number": 34.0,
      "source": "plant_village_classification",
      "original_filename": "RS_HL 2985.JPG"
    }
  },
  "images": [
    {
      "id": 9305796413,
      "width": 256,
      "height": 256,
      "file_name": "image (5061).JPG",
      "size": 20202,
      "format": "JPG",
      "url": "",
      "hash": "",
      "status": "success",
      "original_filename": "RS_HL 2985.JPG",
      "pvc_filename": "fe97769f-3e58-4997-953d-c63c3e917783___RS_HL 2985.JPG"
    }
  ],
  "annotations": [
    {
      "id": 1630478424,
      "image_id": 9305796413,
      "category_id": 2000000024,
      "segmentation": [],
      "area": 302,
      "bbox": [
        4,
        223,
        84,
        13
      ]
    },
    {
      "id": 5958878424,
      "image_id": 9305796413,
      "category_id": 2000000024,
      "segmentation": [],
      "area": 219,
      "bbox": [
        212,
        50,
        28,
        64
      ]
    },
    {
      "id": 3258870424,
      "image_id": 9305796413,
      "category_id": 2000000024,
      "segmentation": [],
      "area": 396,
      "bbox": [
        87,
        29,
        108,
        43
      ]
    },
    {
      "id": 8944698424,
      "image_id": 9305796413,
      "category_id": 2000000024,
      "segmentation": [],
      "area": 415,
      "bbox": [
        185,
        8,
        32,
        41
      ]
    }
  ],
  "categories": [
    {
      "id": 2000000024,
      "name": "healthy",
      "supercategory": "Soybean"
    }
  ]
}