{
  "info": {
    "description": "data",
    "version": "1.0",
    "year": 2025,
    "contributor": "search engine",
    "source": "no_augmentation",
    "license": {
      "name": "Creative Commons Attribution 4.0 International",
      "url": "https://creativecommons.org/licenses/by/4.0/"
    },
    "leaf_info": {
      "leaf_number": 198.0,
      "source": "plant_village_classification",
      "original_filename": "RS_HL 4470.JPG"
    }
  },
  "images": [
    {
      "id": 6133167910,
      "width": 256,
      "height": 256,
      "file_name": "image (1132).JPG",
      "size": 18407,
      "format": "JPG",
      "url": "",
      "hash": "",
      "status": "success",
      "original_filename": "RS_HL 4470.JPG",
      "pvc_filename": "8f59e2db-46d0-4f0a-8210-b3d14891f45f___RS_HL 4470.JPG"
    }
  ],
  "annotations": [
    {
      "id": 1435779921,
      "image_id": 6133167910,
      "category_id": 2000000024,
      "segmentation": [],
      "area": 132,
      "bbox": [
        17,
        229,
        37,
        17
      ]
    },
    {
      "id": 5596722921,
      "image_id": 6133167910,
      "category_id": 2000000024,
      "segmentation": [],
      "area": 558,
      "bbox": [
        55,
        162,
        137,
        68
      ]
    },
    {
      "id": 3851304921,
      "image_id": 6133167910,
      "category_id": 2000000024,
      "segmentation": [],
      "area": 361,
      "bbox": [
        198,
        14,
        42,
        29
      ]
    }
  ],
  "categories": [
    {
      "id": 2000000024,
      "name": "healthy",
      "supercategory": "Soybean"
    }
  ]
}