{
  "info": {
    "description": "data",
    "version": "1.0",
    "year": 2025,
    "contributor": "search engine",
    "source": "no_augmentation",
    "license": {
      "name": "Creative Commons Attribution 4.0 International",
      "url": "https://creativecommons.org/licenses/by/4.0/"
    },
    "leaf_info": {
      "leaf_number": 382.0,
      "source": "plant_village_classification",
      "original_filename": "RS_HL 6040.JPG"
    }
  },
  "images": [
    {
      "id": 3523238042,
      "width": 256,
      "height": 256,
      "file_name": "image (3442).JPG",
      "size": 24018,
      "format": "JPG",
      "url": "",
      "hash": "",
      "status": "success",
      "original_filename": "RS_HL 6040.JPG",
      "pvc_filename": "aeb03fac-cd8a-4f25-85cd-4624cdaea8ed___RS_HL 6040.JPG"
    }
  ],
  "annotations": [
    {
      "id": 1434047053,
      "image_id": 3523238042,
      "category_id": 2000000024,
      "segmentation": [],
      "area": 2251,
      "bbox": [
        7,
        15,
        110,
        233
      ]
    },
    {
      "id": 3588147053,
      "image_id": 3523238042,
      "category_id": 2000000024,
      "segmentation": [],
      "area": 338,
      "bbox": [
        196,
        4,
        42,
        22
      ]
    }
  ],
  "categories": [
    {
      "id": 2000000024,
      "name": "healthy",
      "supercategory": "Soybean"
    }
  ]
}