{
  "info": {
    "description": "data",
    "version": "1.0",
    "year": 2025,
    "contributor": "search engine",
    "source": "augmented",
    "license": {
      "name": "Creative Commons Attribution 4.0 International",
      "url": "https://creativecommons.org/licenses/by/4.0/"
    }
  },
  "images": [
    {
      "id": 2469245564,
      "width": 256,
      "height": 256,
      "file_name": "image (2585).JPG",
      "size": 18185,
      "format": "JPG",
      "url": "",
      "hash": "",
      "status": "success"
    }
  ],
  "annotations": [
    {
      "id": 7585012575,
      "image_id": 2469245564,
      "category_id": 1000000024,
      "segmentation": [],
      "area": 4213,
      "bbox": [
        113,
        6,
        138,
        181
      ]
    },
    {
      "id": 7991087575,
      "image_id": 2469245564,
      "category_id": 1000000024,
      "segmentation": [],
      "area": 128,
      "bbox": [
        126,
        93,
        12,
        30
      ]
    }
  ],
  "categories": [
    {
      "id": 1000000024,
      "name": "healthy",
      "supercategory": "Soybean"
    }
  ]
}