{
  "info": {
    "description": "data",
    "version": "1.0",
    "year": 2025,
    "contributor": "search engine",
    "source": "no_augmentation",
    "license": {
      "name": "Creative Commons Attribution 4.0 International",
      "url": "https://creativecommons.org/licenses/by/4.0/"
    },
    "leaf_info": {
      "leaf_number": 112.0,
      "source": "plant_village_classification",
      "original_filename": "RS_HL 4839.JPG"
    }
  },
  "images": [
    {
      "id": 9831133820,
      "width": 256,
      "height": 256,
      "file_name": "image (3495).JPG",
      "size": 13231,
      "format": "JPG",
      "url": "",
      "hash": "",
      "status": "success",
      "original_filename": "RS_HL 4839.JPG",
      "pvc_filename": "b3d010c1-8c96-4674-b526-04a0874aa543___RS_HL 4839.JPG"
    }
  ],
  "annotations": [],
  "categories": [
    {
      "id": 2000000024,
      "name": "healthy",
      "supercategory": "Soybean"
    }
  ]
}