{
  "info": {
    "description": "data",
    "version": "1.0",
    "year": 2025,
    "contributor": "search engine",
    "source": "no_augmentation",
    "license": {
      "name": "Creative Commons Attribution 4.0 International",
      "url": "https://creativecommons.org/licenses/by/4.0/"
    },
    "leaf_info": {
      "leaf_number": 404.0,
      "source": "plant_village_classification",
      "original_filename": "RS_HL 6318.JPG"
    }
  },
  "images": [
    {
      "id": 8079188871,
      "width": 256,
      "height": 256,
      "file_name": "image (3868).JPG",
      "size": 14198,
      "format": "JPG",
      "url": "",
      "hash": "",
      "status": "success",
      "original_filename": "RS_HL 6318.JPG",
      "pvc_filename": "c012a080-3918-416e-b379-17415fea9be0___RS_HL 6318.JPG"
    }
  ],
  "annotations": [
    {
      "id": 2060603878,
      "image_id": 8079188871,
      "category_id": 2000000024,
      "segmentation": [],
      "area": 247,
      "bbox": [
        151,
        202,
        31,
        49
      ]
    },
    {
      "id": 3301009878,
      "image_id": 8079188871,
      "category_id": 2000000024,
      "segmentation": [],
      "area": 395,
      "bbox": [
        195,
        115,
        48,
        75
      ]
    }
  ],
  "categories": [
    {
      "id": 2000000024,
      "name": "healthy",
      "supercategory": "Soybean"
    }
  ]
}