{
  "info": {
    "description": "data",
    "version": "1.0",
    "year": 2025,
    "contributor": "search engine",
    "source": "augmented",
    "license": {
      "name": "Creative Commons Attribution 4.0 International",
      "url": "https://creativecommons.org/licenses/by/4.0/"
    }
  },
  "images": [
    {
      "id": 1788399447,
      "width": 256,
      "height": 256,
      "file_name": "image (1925).JPG",
      "size": 22953,
      "format": "JPG",
      "url": "",
      "hash": "",
      "status": "success"
    }
  ],
  "annotations": [
    {
      "id": 5945825460,
      "image_id": 1788399447,
      "category_id": 1000000024,
      "segmentation": [],
      "area": 552,
      "bbox": [
        72,
        182,
        63,
        44
      ]
    },
    {
      "id": 2839548460,
      "image_id": 1788399447,
      "category_id": 1000000024,
      "segmentation": [],
      "area": 165,
      "bbox": [
        111,
        200,
        30,
        26
      ]
    },
    {
      "id": 4891799460,
      "image_id": 1788399447,
      "category_id": 1000000024,
      "segmentation": [],
      "area": 1853,
      "bbox": [
        0,
        10,
        79,
        167
      ]
    },
    {
      "id": 8053265460,
      "image_id": 1788399447,
      "category_id": 1000000024,
      "segmentation": [],
      "area": 223,
      "bbox": [
        232,
        83,
        19,
        42
      ]
    },
    {
      "id": 6021051460,
      "image_id": 1788399447,
      "category_id": 1000000024,
      "segmentation": [],
      "area": 510,
      "bbox": [
        181,
        11,
        61,
        50
      ]
    }
  ],
  "categories": [
    {
      "id": 1000000024,
      "name": "healthy",
      "supercategory": "Soybean"
    }
  ]
}