{
  "info": {
    "description": "data",
    "version": "1.0",
    "year": 2025,
    "contributor": "search engine",
    "source": "augmented",
    "license": {
      "name": "Creative Commons Attribution 4.0 International",
      "url": "https://creativecommons.org/licenses/by/4.0/"
    }
  },
  "images": [
    {
      "id": 1001771645,
      "width": 256,
      "height": 256,
      "file_name": "image (2751).JPG",
      "size": 16558,
      "format": "JPG",
      "url": "",
      "hash": "",
      "status": "success"
    }
  ],
  "annotations": [
    {
      "id": 1867620658,
      "image_id": 1001771645,
      "category_id": 1000000024,
      "segmentation": [],
      "area": 1527,
      "bbox": [
        0,
        10,
        103,
        119
      ]
    }
  ],
  "categories": [
    {
      "id": 1000000024,
      "name": "healthy",
      "supercategory": "Soybean"
    }
  ]
}