{
  "info": {
    "description": "data",
    "version": "1.0",
    "year": 2025,
    "contributor": "search engine",
    "source": "no_augmentation",
    "license": {
      "name": "Creative Commons Attribution 4.0 International",
      "url": "https://creativecommons.org/licenses/by/4.0/"
    },
    "leaf_info": {
      "leaf_number": 182.0,
      "source": "plant_village_classification",
      "original_filename": "RS_HL 4335.JPG"
    }
  },
  "images": [
    {
      "id": 5545636690,
      "width": 256,
      "height": 256,
      "file_name": "image (1753).JPG",
      "size": 15203,
      "format": "JPG",
      "url": "",
      "hash": "",
      "status": "success",
      "original_filename": "RS_HL 4335.JPG",
      "pvc_filename": "069aa38e-5d0b-41a9-ad40-a87b943fa209___RS_HL 4335.JPG"
    }
  ],
  "annotations": [
    {
      "id": 4384642700,
      "image_id": 5545636690,
      "category_id": 2000000024,
      "segmentation": [],
      "area": 1844,
      "bbox": [
        14,
        77,
        206,
        168
      ]
    },
    {
      "id": 6216269700,
      "image_id": 5545636690,
      "category_id": 2000000024,
      "segmentation": [],
      "area": 420,
      "bbox": [
        75,
        30,
        37,
        42
      ]
    },
    {
      "id": 6881682700,
      "image_id": 5545636690,
      "category_id": 2000000024,
      "segmentation": [],
      "area": 349,
      "bbox": [
        184,
        20,
        50,
        27
      ]
    }
  ],
  "categories": [
    {
      "id": 2000000024,
      "name": "healthy",
      "supercategory": "Soybean"
    }
  ]
}