{
  "info": {
    "description": "data",
    "version": "1.0",
    "year": 2025,
    "contributor": "search engine",
    "source": "no_augmentation",
    "license": {
      "name": "Creative Commons Attribution 4.0 International",
      "url": "https://creativecommons.org/licenses/by/4.0/"
    },
    "leaf_info": {
      "leaf_number": 138.0,
      "source": "plant_village_classification",
      "original_filename": "RS_HL 5184.JPG"
    }
  },
  "images": [
    {
      "id": 4377402002,
      "width": 256,
      "height": 256,
      "file_name": "image (944).JPG",
      "size": 18682,
      "format": "JPG",
      "url": "",
      "hash": "",
      "status": "success",
      "original_filename": "RS_HL 5184.JPG",
      "pvc_filename": "7c098475-8bec-4582-876b-c44945629b6d___RS_HL 5184.JPG"
    }
  ],
  "annotations": [
    {
      "id": 6385270009,
      "image_id": 4377402002,
      "category_id": 2000000024,
      "segmentation": [],
      "area": 790,
      "bbox": [
        16,
        108,
        218,
        117
      ]
    },
    {
      "id": 7536701009,
      "image_id": 4377402002,
      "category_id": 2000000024,
      "segmentation": [],
      "area": 200,
      "bbox": [
        189,
        7,
        26,
        16
      ]
    }
  ],
  "categories": [
    {
      "id": 2000000024,
      "name": "healthy",
      "supercategory": "Soybean"
    }
  ]
}