{
  "info": {
    "description": "data",
    "version": "1.0",
    "year": 2025,
    "contributor": "search engine",
    "source": "no_augmentation",
    "license": {
      "name": "Creative Commons Attribution 4.0 International",
      "url": "https://creativecommons.org/licenses/by/4.0/"
    },
    "leaf_info": {
      "leaf_number": 144.0,
      "source": "plant_village_classification",
      "original_filename": "RS_HL 5275.JPG"
    }
  },
  "images": [
    {
      "id": 7909214580,
      "width": 256,
      "height": 256,
      "file_name": "image (1036).JPG",
      "size": 18833,
      "format": "JPG",
      "url": "",
      "hash": "",
      "status": "success",
      "original_filename": "RS_HL 5275.JPG",
      "pvc_filename": "8aa2fcc2-5b89-4af2-a44f-021115734231___RS_HL 5275.JPG"
    }
  ],
  "annotations": [
    {
      "id": 5265119587,
      "image_id": 7909214580,
      "category_id": 2000000024,
      "segmentation": [],
      "area": 114,
      "bbox": [
        187,
        227,
        37,
        21
      ]
    },
    {
      "id": 1547664587,
      "image_id": 7909214580,
      "category_id": 2000000024,
      "segmentation": [],
      "area": 2854,
      "bbox": [
        0,
        13,
        140,
        197
      ]
    },
    {
      "id": 7762126587,
      "image_id": 7909214580,
      "category_id": 2000000024,
      "segmentation": [],
      "area": 382,
      "bbox": [
        100,
        22,
        94,
        28
      ]
    }
  ],
  "categories": [
    {
      "id": 2000000024,
      "name": "healthy",
      "supercategory": "Soybean"
    }
  ]
}