{
  "info": {
    "description": "data",
    "version": "1.0",
    "year": 2025,
    "contributor": "search engine",
    "source": "no_augmentation",
    "license": {
      "name": "Creative Commons Attribution 4.0 International",
      "url": "https://creativecommons.org/licenses/by/4.0/"
    },
    "leaf_info": {
      "leaf_number": 1.0,
      "source": "plant_village_classification",
      "original_filename": "RS_HL 2790_final_masked.jpg"
    }
  },
  "images": [
    {
      "id": 4288038804,
      "width": 256,
      "height": 256,
      "file_name": "b7abfde5-1375-49af-8651-62a0a850447c___RS_HL 2790_final_masked.jpg",
      "size": 9158,
      "format": "JPG",
      "url": "",
      "hash": "",
      "status": "success",
      "original_filename": "RS_HL 2790_final_masked.jpg",
      "pvc_filename": "b7abfde5-1375-49af-8651-62a0a850447c___RS_HL 2790_final_masked.jpg"
    }
  ],
  "annotations": [],
  "categories": [
    {
      "id": 2000000001,
      "name": "healthy",
      "supercategory": "Soybean"
    }
  ]
}